{"canvas": [{"name": "Carla", "pos1x": 1088.0, "pos1y": 1092.0, "pos2x": 0.0, "pos2y": 0.0, "split": false}, {"name": "system", "pos1x": 4257.028436018958, "pos1y": 3653.3507109004736, "pos2x": 5494.028436018956, "pos2y": 1954.350710900474, "split": true}, {"name": "a2j", "pos1x": 783.0284360189576, "pos1y": 859.350710900474, "pos2x": 0.0, "pos2y": 0.0, "split": false}, {"name": "PulseAudio JACK Sink", "pos1x": 4926.028436018958, "pos1y": 2591.350710900474, "pos2x": 0.0, "pos2y": 0.0, "split": false}, {"name": "PulseAudio JACK Source", "pos1x": 5331.028436018956, "pos1y": 2915.350710900474, "pos2x": 0.0, "pos2y": 0.0, "split": false}, {"name": "Sawtooth VCA", "pos1x": 3386.0284360189576, "pos1y": 1369.350710900474, "pos2x": 0.0, "pos2y": 0.0, "split": false}, {"name": "LSP Compressor Stereo", "pos1x": 5056.028436018956, "pos1y": 1956.350710900474, "pos2x": 0.0, "pos2y": 0.0, "split": false}, {"name": "Pulse PW", "pos1x": 1604.0284360189576, "pos1y": 1485.350710900474, "pos2x": 0.0, "pos2y": 0.0, "split": false}, {"name": "Sine", "pos1x": 3165.0284360189576, "pos1y": 936.350710900474, "pos2x": 0.0, "pos2y": 0.0, "split": false}, {"name": "Triangle", "pos1x": 3168.0284360189576, "pos1y": 1154.350710900474, "pos2x": 0.0, "pos2y": 0.0, "split": false}, {"name": "Saw", "pos1x": 3173.0284360189576, "pos1y": 1355.350710900474, "pos2x": 0.0, "pos2y": 0.0, "split": false}, {"name": "Pluse", "pos1x": 3172.0284360189576, "pos1y": 1583.350710900474, "pos2x": 0.0, "pos2y": 0.0, "split": false}, {"name": "Sine VCA Exp", "pos1x": 3393.0284360189567, "pos1y": 860.350710900474, "pos2x": 0.0, "pos2y": 0.0, "split": false}, {"name": "AMS Mixer 8 channels", "pos1x": 3701.0, "pos1y": 1323.0, "pos2x": 0.0, "pos2y": 0.0, "split": false}, {"name": "Pluse VCA", "pos1x": 3382.0284360189576, "pos1y": 1592.350710900474, "pos2x": 0.0, "pos2y": 0.0, "split": false}, {"name": "AMS VCA Triangle", "pos1x": 3363.0284360189576, "pos1y": 1172.350710900474, "pos2x": 0.0, "pos2y": 0.0, "split": false}, {"name": "STSP VCA", "pos1x": 3378.0284360189576, "pos1y": 1787.350710900474, "pos2x": 0.0, "pos2y": 0.0, "split": false}, {"name": "S / T / S / P", "pos1x": 3173.0284360189576, "pos1y": 1801.350710900474, "pos2x": 0.0, "pos2y": 0.0, "split": false}, {"name": "16 Step Sequencer", "pos1x": 2467.0284360189576, "pos1y": 1084.350710900474, "pos2x": 0.0, "pos2y": 0.0, "split": false}, {"name": "Drum Clock", "pos1x": 1167.0284360189576, "pos1y": 2610.350710900474, "pos2x": 0.0, "pos2y": 0.0, "split": false}, {"name": "Semitone", "pos1x": 1600.0284360189576, "pos1y": 1276.350710900474, "pos2x": 0.0, "pos2y": 0.0, "split": false}, {"name": "Exp FM Gain", "pos1x": 1597.0284360189576, "pos1y": 1199.350710900474, "pos2x": 0.0, "pos2y": 0.0, "split": false}, {"name": "Gain Decay", "pos1x": 1597.0284360189576, "pos1y": 1009.350710900474, "pos2x": 0.0, "pos2y": 0.0, "split": false}, {"name": "Saw Edge", "pos1x": 1612.0, "pos1y": 1398.0, "pos2x": 0.0, "pos2y": 0.0, "split": false}, {"name": "Pluse Edge", "pos1x": 1594.0284360189576, "pos1y": 1558.350710900474, "pos2x": 0.0, "pos2y": 0.0, "split": false}, {"name": "Wedge Gate Open", "pos1x": 2243.0284360189576, "pos1y": 1092.350710900474, "pos2x": 0.0, "pos2y": 0.0, "split": false}, {"name": "MIDI-Trigger", "pos1x": 2857.0284360189576, "pos1y": 2717.350710900474, "pos2x": 0.0, "pos2y": 0.0, "split": false}, {"name": "AMS Stereo Mixer 8 channels", "pos1x": 4295.028436018958, "pos1y": 2226.350710900474, "pos2x": 0.0, "pos2y": 0.0, "split": false}, {"name": "EsPhaser", "pos1x": 3500.0284360189576, "pos1y": 2747.350710900474, "pos2x": 0.0, "pos2y": 0.0, "split": false}, {"name": "x42-Autotune", "pos1x": 3753.0284360189576, "pos1y": 2739.350710900474, "pos2x": 0.0, "pos2y": 0.0, "split": false}, {"name": "x42-Autotune (3)", "pos1x": 3751.0284360189576, "pos1y": 2814.350710900474, "pos2x": 0.0, "pos2y": 0.0, "split": false}, {"name": "MIDI Generator", "pos1x": 3529.0284360189576, "pos1y": 2852.350710900474, "pos2x": 0.0, "pos2y": 0.0, "split": false}, {"name": "AMS Stereo Mixer 8 channels (4)", "pos1x": 4727.028436018958, "pos1y": 1955.350710900474, "pos2x": 0.0, "pos2y": 0.0, "split": false}, {"name": "FDNCymbal", "pos1x": 3268.0284360189576, "pos1y": 2744.350710900474, "pos2x": 0.0, "pos2y": 0.0, "split": false}, {"name": "AMS Slew Limiter", "pos1x": 2918.0284360189576, "pos1y": 2821.350710900474, "pos2x": 0.0, "pos2y": 0.0, "split": false}, {"name": "AMS Hysteresis", "pos1x": 3101.0284360189576, "pos1y": 2829.350710900474, "pos2x": 0.0, "pos2y": 0.0, "split": false}, {"name": "AMS VC Switch", "pos1x": 2128.0284360189576, "pos1y": 2854.350710900474, "pos2x": 0.0, "pos2y": 0.0, "split": false}, {"name": "Clock Divider Slower", "pos1x": 1664.0284360189576, "pos1y": 2442.350710900474, "pos2x": 0.0, "pos2y": 0.0, "split": false}, {"name": "Clock Divider Faster", "pos1x": 1666.0284360189576, "pos1y": 2707.350710900474, "pos2x": 0.0, "pos2y": 0.0, "split": false}, {"name": "Drums Gate", "pos1x": 1418.0284360189576, "pos1y": 2572.350710900474, "pos2x": 0.0, "pos2y": 0.0, "split": false}, {"name": "Kick Gate", "pos1x": 2120.0284360189576, "pos1y": 1974.350710900474, "pos2x": 0.0, "pos2y": 0.0, "split": false}, {"name": "Snare Gate", "pos1x": 2129.0284360189576, "pos1y": 2399.350710900474, "pos2x": 0.0, "pos2y": 0.0, "split": false}, {"name": "MIDI to CV trigger", "pos1x": 815.0284360189576, "pos1y": 2442.350710900474, "pos2x": 0.0, "pos2y": 0.0, "split": false}, {"name": "Snare Sine", "pos1x": 2790.0284360189576, "pos1y": 2253.350710900474, "pos2x": 0.0, "pos2y": 0.0, "split": false}, {"name": "Snare Noise", "pos1x": 2711.0284360189576, "pos1y": 2437.350710900474, "pos2x": 0.0, "pos2y": 0.0, "split": false}, {"name": "Freq Env (2)", "pos1x": 2506.0284360189576, "pos1y": 2332.350710900474, "pos2x": 0.0, "pos2y": 0.0, "split": false}, {"name": "Snare Sine Gain", "pos1x": 2984.0284360189576, "pos1y": 2252.350710900474, "pos2x": 0.0, "pos2y": 0.0, "split": false}, {"name": "AMS VCA Exp (3)", "pos1x": 2982.0284360189576, "pos1y": 2407.350710900474, "pos2x": 0.0, "pos2y": 0.0, "split": false}, {"name": "AMS Stereo Mixer 4 channels", "pos1x": 3260.0284360189576, "pos1y": 2253.350710900474, "pos2x": 0.0, "pos2y": 0.0, "split": false}, {"name": "AMS LFO", "pos1x": 2510.0284360189576, "pos1y": 2901.350710900474, "pos2x": 0.0, "pos2y": 0.0, "split": false}, {"name": "Attenuverter Booster", "pos1x": 2714.0284360189576, "pos1y": 2897.350710900474, "pos2x": 0.0, "pos2y": 0.0, "split": false}, {"name": "AMS Noise2 (2)", "pos1x": 2904.0284360189576, "pos1y": 3160.3507109004736, "pos2x": 0.0, "pos2y": 0.0, "split": false}, {"name": "AMS VCA Exp (2)", "pos1x": 3247.0284360189576, "pos1y": 3190.3507109004736, "pos2x": 0.0, "pos2y": 0.0, "split": false}, {"name": "Hi-hat Gate", "pos1x": 2112.0284360189576, "pos1y": 3197.3507109004736, "pos2x": 0.0, "pos2y": 0.0, "split": false}, {"name": "Freq Env (3)", "pos1x": 2941.0284360189576, "pos1y": 3224.3507109004736, "pos2x": 0.0, "pos2y": 0.0, "split": false}, {"name": "Moog High-Pass Filter 1", "pos1x": 3676.0284360189576, "pos1y": 3184.3507109004736, "pos2x": 0.0, "pos2y": 0.0, "split": false}, {"name": "AMS LFO (2)", "pos1x": 2501.0284360189576, "pos1y": 3301.3507109004736, "pos2x": 0.0, "pos2y": 0.0, "split": false}, {"name": "Amplitude Modifier", "pos1x": 2762.0284360189576, "pos1y": 3285.3507109004736, "pos2x": 0.0, "pos2y": 0.0, "split": false}, {"name": "Freq Decay", "pos1x": 1603.0284360189576, "pos1y": 1119.350710900474, "pos2x": 0.0, "pos2y": 0.0, "split": false}, {"name": "LSP Compressor Stereo (2)", "pos1x": 4192.028436018958, "pos1y": 1324.350710900474, "pos2x": 0.0, "pos2y": 0.0, "split": false}, {"name": "Glame Lowpass Filter", "pos1x": 3952.0284360189576, "pos1y": 1294.350710900474, "pos2x": 0.0, "pos2y": 0.0, "split": false}, {"name": "Glame Lowpass Filter (2)", "pos1x": 3942.0284360189576, "pos1y": 1379.350710900474, "pos2x": 0.0, "pos2y": 0.0, "split": false}, {"name": "DIN Meter (Stereo)", "pos1x": 3203.0284360189576, "pos1y": 3341.3507109004736, "pos2x": 0.0, "pos2y": 0.0, "split": false}, {"name": "CV to Audio (3)", "pos1x": 2975.0284360189576, "pos1y": 3391.3507109004736, "pos2x": 0.0, "pos2y": 0.0, "split": false}, {"name": "Simple Scope (Mono)", "pos1x": 3209.0284360189576, "pos1y": 3444.3507109004736, "pos2x": 0.0, "pos2y": 0.0, "split": false}, {"name": "Range Translator", "pos1x": 2765.0284360189576, "pos1y": 3397.3507109004736, "pos2x": 0.0, "pos2y": 0.0, "split": false}, {"name": "Simple Scope (4 channel) (3)", "pos1x": 2212.0284360189576, "pos1y": 2261.350710900474, "pos2x": 0.0, "pos2y": 0.0, "split": false}, {"name": "Control of Gates", "pos1x": 801.0284360189576, "pos1y": 1985.350710900474, "pos2x": 0.0, "pos2y": 0.0, "split": false}, {"name": "Cra Cymb Gate", "pos1x": 2076.0284360189576, "pos1y": 2597.350710900474, "pos2x": 0.0, "pos2y": 0.0, "split": false}, {"name": "CV to Audio", "pos1x": 2500.0284360189576, "pos1y": 2687.350710900474, "pos2x": 0.0, "pos2y": 0.0, "split": false}, {"name": "Control of Kick", "pos1x": 916.0284360189576, "pos1y": 1159.350710900474, "pos2x": 0.0, "pos2y": 0.0, "split": false}, {"name": "Gain Level", "pos1x": 1341.0284360189576, "pos1y": 1648.350710900474, "pos2x": 0.0, "pos2y": 0.0, "split": false}, {"name": "Gain Curve", "pos1x": 1341.0284360189576, "pos1y": 1726.350710900474, "pos2x": 0.0, "pos2y": 0.0, "split": false}, {"name": "Freq Level", "pos1x": 1341.0284360189576, "pos1y": 1804.350710900474, "pos2x": 0.0, "pos2y": 0.0, "split": false}, {"name": "Freq Curve", "pos1x": 1341.0284360189576, "pos1y": 1882.350710900474, "pos2x": 0.0, "pos2y": 0.0, "split": false}, {"name": "Simple Scope (4 channel)", "pos1x": 3317.0284360189576, "pos1y": 712.350710900474, "pos2x": 0.0, "pos2y": 0.0, "split": false}, {"name": "Gain Env", "pos1x": 2470.0284360189576, "pos1y": 1295.350710900474, "pos2x": 0.0, "pos2y": 0.0, "split": false}, {"name": "Freq Env", "pos1x": 2479.0284360189576, "pos1y": 1604.350710900474, "pos2x": 0.0, "pos2y": 0.0, "split": false}]}